AUTHORS
LICENSE
MANIFEST.in
README.md
setup.cfg
setup.py
tests/__init__.py
uts/__init__.py
uts/c99.py
uts/texttiling.py
uts/utils.py
uts.egg-info/PKG-INFO
uts.egg-info/SOURCES.txt
uts.egg-info/dependency_links.txt
uts.egg-info/requires.txt
uts.egg-info/top_level.txt