Metadata-Version: 1.1
Name: uts
Version: 0.0.4
Summary: python package for unsupervised text segmentation
Home-page: https://github.com/intfloat/uts
Author: Liang Wang
Author-email: wangliangpeking@gmail.com
License: MIT
Platform: UNKNOWN
Classifier: Development Status :: 3 - Alpha
Classifier: Environment :: Console
Classifier: Intended Audience :: Developers
Classifier: Intended Audience :: Information Technology
Classifier: License :: OSI Approved :: MIT License
Classifier: Operating System :: OS Independent
Classifier: Programming Language :: Python
